README.rst
setup.cfg
setup.py
cassandra_quickstart/__init__.py
cassandra_quickstart/config.py
cassandra_quickstart/java.py
cassandra_quickstart/main.py
cassandra_quickstart/util.py
cassandra_quickstart.egg-info/PKG-INFO
cassandra_quickstart.egg-info/SOURCES.txt
cassandra_quickstart.egg-info/dependency_links.txt
cassandra_quickstart.egg-info/entry_points.txt
cassandra_quickstart.egg-info/not-zip-safe
cassandra_quickstart.egg-info/requires.txt
cassandra_quickstart.egg-info/top_level.txt