Metadata-Version: 1.0
Name: cassandra-quickstart
Version: 0.1.1
Summary: Quickstart tool for installing and managing Cassandra in development environments
Home-page: https://github.com/EnigmaCurry/cassandra-quickstart
Author: Ryan McGuire
Author-email: ryan@datastax.com
License: UNKNOWN
Platform: UNKNOWN
